aury/__init__.py
aury/agents/__init__.py
aury/agents/plugin.py
aury/agents/a2a/__init__.py
aury/agents/backends/__init__.py
aury/agents/backends/sandbox.py
aury/agents/backends/shell.py
aury/agents/backends/artifact/__init__.py
aury/agents/backends/artifact/memory.py
aury/agents/backends/artifact/types.py
aury/agents/backends/code/__init__.py
aury/agents/backends/file/__init__.py
aury/agents/backends/file/local.py
aury/agents/backends/file/types.py
aury/agents/backends/hitl/__init__.py
aury/agents/backends/hitl/memory.py
aury/agents/backends/hitl/types.py
aury/agents/backends/invocation/__init__.py
aury/agents/backends/invocation/memory.py
aury/agents/backends/invocation/types.py
aury/agents/backends/memory/__init__.py
aury/agents/backends/memory/memory.py
aury/agents/backends/memory/types.py
aury/agents/backends/message/__init__.py
aury/agents/backends/message/memory.py
aury/agents/backends/message/types.py
aury/agents/backends/session/__init__.py
aury/agents/backends/session/memory.py
aury/agents/backends/session/types.py
aury/agents/backends/shell/__init__.py
aury/agents/backends/shell/local.py
aury/agents/backends/shell/types.py
aury/agents/backends/snapshot/__init__.py
aury/agents/backends/snapshot/git.py
aury/agents/backends/snapshot/hybrid.py
aury/agents/backends/snapshot/memory.py
aury/agents/backends/snapshot/types.py
aury/agents/backends/state/__init__.py
aury/agents/backends/state/composite.py
aury/agents/backends/state/file.py
aury/agents/backends/state/memory.py
aury/agents/backends/state/sqlite.py
aury/agents/backends/state/types.py
aury/agents/backends/subagent/__init__.py
aury/agents/cli/__init__.py
aury/agents/cli/chat.py
aury/agents/cli/config.py
aury/agents/cli/extensions.py
aury/agents/cli/main.py
aury/agents/cli/session.py
aury/agents/cli/workflow.py
aury/agents/context_providers/__init__.py
aury/agents/context_providers/artifact.py
aury/agents/context_providers/base.py
aury/agents/context_providers/memory.py
aury_agent-0.0.13.dist-info/METADATA
aury_agent-0.0.13.dist-info/WHEEL
aury_agent-0.0.13.dist-info/entry_points.txt
aury_agent-0.0.13.dist-info/RECORD
